aft_pytorch/__init__.py
aft_pytorch/aft_pytorch.py
aft_pytorch-0.2.2.dist-info/LICENSE
aft_pytorch-0.2.2.dist-info/METADATA
aft_pytorch-0.2.2.dist-info/WHEEL
aft_pytorch-0.2.2.dist-info/top_level.txt
aft_pytorch-0.2.2.dist-info/RECORD
